spatiotemporal_data_library/__init__.py
spatiotemporal_data_library/config.py
spatiotemporal_data_library/fetch.py
spatiotemporal_data_library/utils.py
spatiotemporal_data_library/adapters/__init__.py
spatiotemporal_data_library/adapters/base.py
spatiotemporal_data_library/adapters/era5.py
spatiotemporal_data_library/adapters/podaac.py
spatiotemporal_data_library/adapters/sfmr.py
spatiotemporal_data_library/adapters/smap_rss.py
spatiotemporal_data_library-0.1.1.dist-info/licenses/LICENSE
tests/__init__.py
tests/conftest.py
tests/test_spatiotemporal_data_library.py
spatiotemporal_data_library-0.1.1.dist-info/METADATA
spatiotemporal_data_library-0.1.1.dist-info/WHEEL
spatiotemporal_data_library-0.1.1.dist-info/top_level.txt
spatiotemporal_data_library-0.1.1.dist-info/RECORD
