Metadata-Version: 2.4
Name: spatiotemporal_data_library
Version: 0.1.1
Summary: A Python library for unified access to multi-source spatiotemporal Earth observation data (ERA5, PO.DAAC, SMAP, SFMR, etc.)
Home-page: https://github.com/yourusername/spatiotemporal_data_library
Author: Your Name
Author-email: your.email@example.com
License: MIT
Project-URL: Documentation, https://github.com/yourusername/spatiotemporal_data_library
Project-URL: Source, https://github.com/yourusername/spatiotemporal_data_library
Project-URL: Tracker, https://github.com/yourusername/spatiotemporal_data_library/issues
Keywords: spatiotemporal,earth observation,remote sensing,ERA5,PO.DAAC,SMAP,SFMR,xarray,meteorology,oceanography
Classifier: Development Status :: 3 - Alpha
Classifier: Intended Audience :: Science/Research
Classifier: Intended Audience :: Developers
Classifier: Topic :: Scientific/Engineering :: Atmospheric Science
Classifier: Topic :: Scientific/Engineering :: GIS
Classifier: Topic :: Scientific/Engineering :: Information Analysis
Classifier: Programming Language :: Python :: 3
Classifier: Programming Language :: Python :: 3.8
Classifier: Programming Language :: Python :: 3.9
Classifier: Programming Language :: Python :: 3.10
Classifier: Programming Language :: Python :: 3.11
Classifier: License :: OSI Approved :: MIT License
Classifier: Operating System :: OS Independent
Classifier: Natural Language :: English
Classifier: Natural Language :: Chinese (Simplified)
Requires-Python: >=3.8
License-File: LICENSE
Requires-Dist: xarray>=2022.0
Requires-Dist: pandas>=1.3
Requires-Dist: requests>=2.25
Requires-Dist: cdsapi>=0.5
Requires-Dist: netCDF4>=1.5
Provides-Extra: test
Requires-Dist: pytest>=7.0; extra == "test"
Requires-Dist: pytest-cov>=4.0; extra == "test"
Requires-Dist: xarray>=2022.0; extra == "test"
Requires-Dist: pandas>=1.3; extra == "test"
Requires-Dist: requests>=2.25; extra == "test"
Requires-Dist: cdsapi>=0.5; extra == "test"
Requires-Dist: netCDF4>=1.5; extra == "test"
Dynamic: author
Dynamic: author-email
Dynamic: classifier
Dynamic: description
Dynamic: description-content-type
Dynamic: home-page
Dynamic: keywords
Dynamic: license
Dynamic: license-file
Dynamic: project-url
Dynamic: provides-extra
Dynamic: requires-dist
Dynamic: requires-python
Dynamic: summary
